odoo8_addon_web_x2many_add_button_position-8.0.1.0.0-py2.7-nspkg.pth
odoo_addons/web_x2many_add_button_position/__openerp__.py
odoo_addons/web_x2many_add_button_position/__init__.py
odoo_addons/web_x2many_add_button_position/README.rst
odoo_addons/web_x2many_add_button_position/templates/assets.xml
odoo_addons/web_x2many_add_button_position/static/src/js/web_x2many_add_button_position.js
odoo8_addon_web_x2many_add_button_position-8.0.1.0.0.dist-info/top_level.txt
odoo8_addon_web_x2many_add_button_position-8.0.1.0.0.dist-info/WHEEL
odoo8_addon_web_x2many_add_button_position-8.0.1.0.0.dist-info/RECORD
odoo8_addon_web_x2many_add_button_position-8.0.1.0.0.dist-info/metadata.json
odoo8_addon_web_x2many_add_button_position-8.0.1.0.0.dist-info/DESCRIPTION.rst
odoo8_addon_web_x2many_add_button_position-8.0.1.0.0.dist-info/METADATA
odoo8_addon_web_x2many_add_button_position-8.0.1.0.0.dist-info/namespace_packages.txt
