Metadata-Version: 2.0
Name: odoo8-addon-web-x2many-add-button-position
Version: 8.0.1.0.0
Summary: Configurable position for the 'Add an Item' button
Home-page: http://www.onestein.eu
Author: Onestein,Odoo Community Association (OCA)
Author-email: support@odoo-community.org
License: UNKNOWN
Platform: UNKNOWN
Requires-Dist: odoo (<9.0a,>=8.0a)
Classifier: Programming Language :: Python :: 2.7
Classifier: Framework :: Odoo
